Metadata-Version: 1.0
Name: GnBProbabilities
Version: 1.0
Summary: Gaussian and Binomial distributions
Home-page: UNKNOWN
Author: Seema Savadi
Author-email: seemasavadi@gmail.com
License: UNKNOWN
Platform: UNKNOWN
